{
"meta":{"launch_mode":"Train","name":"experiment","iteration_count":1000,"learn_metrics":[{"best_value":"Min","name":"Logloss"}],"test_sets":[],"test_metrics":[],"learn_sets":["learn"]},
"iterations":[
{"learn":[0.6836586286],"iteration":0,"passed_time":0.0358085511,"remaining_time":35.77274255},
{"learn":[0.6774965081],"iteration":1,"passed_time":0.05680731793,"remaining_time":28.34685165},
{"learn":[0.6691923294],"iteration":2,"passed_time":0.09150303445,"remaining_time":30.40950845},
{"learn":[0.6601526491],"iteration":3,"passed_time":0.1190329895,"remaining_time":29.63921437},
{"learn":[0.6503827804],"iteration":4,"passed_time":0.1598079833,"remaining_time":31.80178867},
{"learn":[0.6418766578],"iteration":5,"passed_time":0.1915923158,"remaining_time":31.74046032},
{"learn":[0.6341867425],"iteration":6,"passed_time":0.2246449583,"remaining_time":31.86749194},
{"learn":[0.6271613869],"iteration":7,"passed_time":0.2501803738,"remaining_time":31.02236636},
{"learn":[0.6207807548],"iteration":8,"passed_time":0.2735181954,"remaining_time":30.1173924},
{"learn":[0.6141843327],"iteration":9,"passed_time":0.2958525194,"remaining_time":29.28939942},
{"learn":[0.61005768],"iteration":10,"passed_time":0.3119198272,"remaining_time":28.0444281},
{"learn":[0.6043831918],"iteration":11,"passed_time":0.3306806041,"remaining_time":27.2260364},
{"learn":[0.5988483585],"iteration":12,"passed_time":0.3546302222,"remaining_time":26.92461764},
{"learn":[0.5929834785],"iteration":13,"passed_time":0.3824140247,"remaining_time":26.93287345},
{"learn":[0.5889571601],"iteration":14,"passed_time":0.3999960074,"remaining_time":26.26640448},
{"learn":[0.5819713067],"iteration":15,"passed_time":0.4332358843,"remaining_time":26.64400688},
{"learn":[0.5752664822],"iteration":16,"passed_time":0.4678958996,"remaining_time":27.05539231},
{"learn":[0.5706080167],"iteration":17,"passed_time":0.4990335045,"remaining_time":27.22505008},
{"learn":[0.5656740295],"iteration":18,"passed_time":0.529639308,"remaining_time":27.34611374},
{"learn":[0.5609965137],"iteration":19,"passed_time":0.5531603768,"remaining_time":27.10485846},
{"learn":[0.5564463579],"iteration":20,"passed_time":0.5766487079,"remaining_time":26.88281357},
{"learn":[0.5514754137],"iteration":21,"passed_time":0.6050253168,"remaining_time":26.89612544},
{"learn":[0.5465057518],"iteration":22,"passed_time":0.6389039708,"remaining_time":27.13952954},
{"learn":[0.5429311627],"iteration":23,"passed_time":0.6583048364,"remaining_time":26.77106335},
{"learn":[0.5384373825],"iteration":24,"passed_time":0.6938051098,"remaining_time":27.05839928},
{"learn":[0.5341750697],"iteration":25,"passed_time":0.7279162897,"remaining_time":27.26886409},
{"learn":[0.5297572926],"iteration":26,"passed_time":0.7591319396,"remaining_time":27.35686582},
{"learn":[0.5265191044],"iteration":27,"passed_time":0.7822915856,"remaining_time":27.15669361},
{"learn":[0.5222049692],"iteration":28,"passed_time":0.8193754887,"remaining_time":27.43495171},
{"learn":[0.5183924923],"iteration":29,"passed_time":0.8553571404,"remaining_time":27.65654754},
{"learn":[0.5154925204],"iteration":30,"passed_time":0.881401528,"remaining_time":27.55090583},
{"learn":[0.5130332233],"iteration":31,"passed_time":0.9129436195,"remaining_time":27.61654449},
{"learn":[0.5109792972],"iteration":32,"passed_time":0.9373314154,"remaining_time":27.46665087},
{"learn":[0.5071143817],"iteration":33,"passed_time":0.9858750352,"remaining_time":28.01044953},
{"learn":[0.503755331],"iteration":34,"passed_time":1.020950509,"remaining_time":28.14906403},
{"learn":[0.5004023193],"iteration":35,"passed_time":1.053028958,"remaining_time":28.19777543},
{"learn":[0.4981699552],"iteration":36,"passed_time":1.077934116,"remaining_time":28.05542037},
{"learn":[0.4966933656],"iteration":37,"passed_time":1.099715213,"remaining_time":27.84015882},
{"learn":[0.4941757321],"iteration":38,"passed_time":1.137430942,"remaining_time":28.02746502},
{"learn":[0.4921368334],"iteration":39,"passed_time":1.163808258,"remaining_time":27.93139819},
{"learn":[0.4900183314],"iteration":40,"passed_time":1.191451281,"remaining_time":27.86833605},
{"learn":[0.4881150066],"iteration":41,"passed_time":1.234860799,"remaining_time":28.16658681},
{"learn":[0.48602253],"iteration":42,"passed_time":1.269986837,"remaining_time":28.26459076},
{"learn":[0.4842239934],"iteration":43,"passed_time":1.295445252,"remaining_time":28.14649229},
{"learn":[0.4828718356],"iteration":44,"passed_time":1.317780023,"remaining_time":27.9662205},
{"learn":[0.4803595268],"iteration":45,"passed_time":1.350365357,"remaining_time":28.00540328},
{"learn":[0.4779868032],"iteration":46,"passed_time":1.386037305,"remaining_time":28.10411812},
{"learn":[0.4763022206],"iteration":47,"passed_time":1.412340118,"remaining_time":28.01141233},
{"learn":[0.4738707393],"iteration":48,"passed_time":1.447520136,"remaining_time":28.09370712},
{"learn":[0.4721135419],"iteration":49,"passed_time":1.477084635,"remaining_time":28.06460806},
{"learn":[0.4696044715],"iteration":50,"passed_time":1.507314253,"remaining_time":28.04786718},
{"learn":[0.4681824894],"iteration":51,"passed_time":1.535975215,"remaining_time":28.00200969},
{"learn":[0.4666416706],"iteration":52,"passed_time":1.565014673,"remaining_time":27.96356406},
{"learn":[0.464577707],"iteration":53,"passed_time":1.601451624,"remaining_time":28.05505993},
{"learn":[0.4630602432],"iteration":54,"passed_time":1.631041303,"remaining_time":28.02425512},
{"learn":[0.4622937091],"iteration":55,"passed_time":1.652320991,"remaining_time":27.853411},
{"learn":[0.4609513126],"iteration":56,"passed_time":1.679466904,"remaining_time":27.78486475},
{"learn":[0.4598093901],"iteration":57,"passed_time":1.706959202,"remaining_time":27.72337187},
{"learn":[0.4591166073],"iteration":58,"passed_time":1.726441641,"remaining_time":27.53528109},
{"learn":[0.4576492659],"iteration":59,"passed_time":1.760419112,"remaining_time":27.57989942},
{"learn":[0.4569706413],"iteration":60,"passed_time":1.789536547,"remaining_time":27.54712815},
{"learn":[0.4553371763],"iteration":61,"passed_time":1.820229331,"remaining_time":27.53830827},
{"learn":[0.454490385],"iteration":62,"passed_time":1.851630441,"remaining_time":27.53932894},
{"learn":[0.4527031661],"iteration":63,"passed_time":1.889879659,"remaining_time":27.63949001},
{"learn":[0.4510747271],"iteration":64,"passed_time":1.930335681,"remaining_time":27.76713633},
{"learn":[0.4499587323],"iteration":65,"passed_time":1.961580872,"remaining_time":27.75934144},
{"learn":[0.4494159253],"iteration":66,"passed_time":1.985648745,"remaining_time":27.65089968},
{"learn":[0.4488564398],"iteration":67,"passed_time":2.006411903,"remaining_time":27.4996455},
{"learn":[0.4482504217],"iteration":68,"passed_time":2.029079017,"remaining_time":27.37786326},
{"learn":[0.447651549],"iteration":69,"passed_time":2.05100211,"remaining_time":27.24902803},
{"learn":[0.4471645968],"iteration":70,"passed_time":2.084615005,"remaining_time":27.27615972},
{"learn":[0.4466011253],"iteration":71,"passed_time":2.110390317,"remaining_time":27.20058631},
{"learn":[0.4458076514],"iteration":72,"passed_time":2.136402299,"remaining_time":27.12938261},
{"learn":[0.4448891452],"iteration":73,"passed_time":2.167660886,"remaining_time":27.12505379},
{"learn":[0.443902814],"iteration":74,"passed_time":2.196693292,"remaining_time":27.0925506},
{"learn":[0.4431956505],"iteration":75,"passed_time":2.217412521,"remaining_time":26.95906802},
{"learn":[0.442513823],"iteration":76,"passed_time":2.239452823,"remaining_time":26.84435007},
{"learn":[0.4416259448],"iteration":77,"passed_time":2.267093158,"remaining_time":26.79820374},
{"learn":[0.4412745319],"iteration":78,"passed_time":2.285526445,"remaining_time":26.64518805},
{"learn":[0.4397880448],"iteration":79,"passed_time":2.317510767,"remaining_time":26.65137381},
{"learn":[0.4393558664],"iteration":80,"passed_time":2.340122007,"remaining_time":26.55027314},
{"learn":[0.4380650567],"iteration":81,"passed_time":2.37189753,"remaining_time":26.55368211},
{"learn":[0.4374362887],"iteration":82,"passed_time":2.39082897,"remaining_time":26.41433935},
{"learn":[0.4370617709],"iteration":83,"passed_time":2.40876867,"remaining_time":26.26704883},
{"learn":[0.4366954572],"iteration":84,"passed_time":2.429378464,"remaining_time":26.15154464},
{"learn":[0.4359478935],"iteration":85,"passed_time":2.459737502,"remaining_time":26.14186136},
{"learn":[0.4349687741],"iteration":86,"passed_time":2.48718183,"remaining_time":26.10111507},
{"learn":[0.4347100881],"iteration":87,"passed_time":2.507712275,"remaining_time":25.98901812},
{"learn":[0.4339683553],"iteration":88,"passed_time":2.533996399,"remaining_time":25.93787325},
{"learn":[0.4335496344],"iteration":89,"passed_time":2.562948509,"remaining_time":25.91425715},
{"learn":[0.4330347591],"iteration":90,"passed_time":2.58598523,"remaining_time":25.83143488},
{"learn":[0.4321781997],"iteration":91,"passed_time":2.621336279,"remaining_time":25.87144936},
{"learn":[0.4312848909],"iteration":92,"passed_time":2.660500294,"remaining_time":25.94702975},
{"learn":[0.4303574788],"iteration":93,"passed_time":2.700289228,"remaining_time":26.02619192},
{"learn":[0.4300909656],"iteration":94,"passed_time":2.718079153,"remaining_time":25.89328035},
{"learn":[0.429648376],"iteration":95,"passed_time":2.74290932,"remaining_time":25.82906277},
{"learn":[0.4291782282],"iteration":96,"passed_time":2.78589876,"remaining_time":25.93470701},
{"learn":[0.4288378938],"iteration":97,"passed_time":2.810154128,"remaining_time":25.86488799},
{"learn":[0.4285786572],"iteration":98,"passed_time":2.839148522,"remaining_time":25.83911937},
{"learn":[0.4280100747],"iteration":99,"passed_time":2.874375108,"remaining_time":25.86937597},
{"learn":[0.4275669489],"iteration":100,"passed_time":2.9006543,"remaining_time":25.8186952},
{"learn":[0.4271736296],"iteration":101,"passed_time":2.929157601,"remaining_time":25.78807378},
{"learn":[0.4268878431],"iteration":102,"passed_time":2.956471474,"remaining_time":25.74713507},
{"learn":[0.4265358859],"iteration":103,"passed_time":2.979783552,"remaining_time":25.67198137},
{"learn":[0.4262008858],"iteration":104,"passed_time":3.002163785,"remaining_time":25.58987226},
{"learn":[0.4258300701],"iteration":105,"passed_time":3.040870082,"remaining_time":25.64658352},
{"learn":[0.4254930426],"iteration":106,"passed_time":3.075495463,"remaining_time":25.66745279},
{"learn":[0.425166737],"iteration":107,"passed_time":3.106559836,"remaining_time":25.65788309},
{"learn":[0.4243445239],"iteration":108,"passed_time":3.145900784,"remaining_time":25.7155743},
{"learn":[0.4240536207],"iteration":109,"passed_time":3.169803258,"remaining_time":25.64659},
{"learn":[0.4238811766],"iteration":110,"passed_time":3.187859652,"remaining_time":25.53159667},
{"learn":[0.4238066094],"iteration":111,"passed_time":3.206033801,"remaining_time":25.41926799},
{"learn":[0.4236109995],"iteration":112,"passed_time":3.233963632,"remaining_time":25.38518355},
{"learn":[0.4226449597],"iteration":113,"passed_time":3.267115912,"remaining_time":25.3917956},
{"learn":[0.4220176044],"iteration":114,"passed_time":3.294736788,"remaining_time":25.35514833},
{"learn":[0.4216827642],"iteration":115,"passed_time":3.324794737,"remaining_time":25.33722886},
{"learn":[0.4214678901],"iteration":116,"passed_time":3.350181294,"remaining_time":25.28384686},
{"learn":[0.421259847],"iteration":117,"passed_time":3.374469842,"remaining_time":25.22273221},
{"learn":[0.4205686077],"iteration":118,"passed_time":3.409819534,"remaining_time":25.24412613},
{"learn":[0.420317296],"iteration":119,"passed_time":3.434946571,"remaining_time":25.18960818},
{"learn":[0.4201860729],"iteration":120,"passed_time":3.458824046,"remaining_time":25.12649865},
{"learn":[0.4200571238],"iteration":121,"passed_time":3.486755184,"remaining_time":25.09320534},
{"learn":[0.4198594687],"iteration":122,"passed_time":3.514826023,"remaining_time":25.0609953},
{"learn":[0.419427162],"iteration":123,"passed_time":3.540024534,"remaining_time":25.00856041},
{"learn":[0.419144448],"iteration":124,"passed_time":3.561978284,"remaining_time":24.93384799},
{"learn":[0.4188052469],"iteration":125,"passed_time":3.589524239,"remaining_time":24.89876337},
{"learn":[0.418559347],"iteration":126,"passed_time":3.618868846,"remaining_time":24.87616143},
{"learn":[0.4184425537],"iteration":127,"passed_time":3.639833689,"remaining_time":24.79636701},
{"learn":[0.4182701796],"iteration":128,"passed_time":3.667819277,"remaining_time":24.7648883},
{"learn":[0.4178234116],"iteration":129,"passed_time":3.707295442,"remaining_time":24.81036181},
{"learn":[0.4174673606],"iteration":130,"passed_time":3.741313815,"remaining_time":24.81833362},
{"learn":[0.4167886156],"iteration":131,"passed_time":3.777832955,"remaining_time":24.84211367},
{"learn":[0.4166135014],"iteration":132,"passed_time":3.815011636,"remaining_time":24.86928638},
{"learn":[0.4158369567],"iteration":133,"passed_time":3.852588561,"remaining_time":24.89807234},
{"learn":[0.4157407602],"iteration":134,"passed_time":3.871893058,"remaining_time":24.80879626},
{"learn":[0.4155007371],"iteration":135,"passed_time":3.908660941,"remaining_time":24.83149304},
{"learn":[0.4154372172],"iteration":136,"passed_time":3.923891207,"remaining_time":24.71765045},
{"learn":[0.4151837831],"iteration":137,"passed_time":3.948850483,"remaining_time":24.66600809},
{"learn":[0.41509687],"iteration":138,"passed_time":3.965052081,"remaining_time":24.56050246},
{"learn":[0.4150027763],"iteration":139,"passed_time":3.989637314,"remaining_time":24.50777207},
{"learn":[0.4148564255],"iteration":140,"passed_time":4.009443725,"remaining_time":24.42632737},
{"learn":[0.4147746402],"iteration":141,"passed_time":4.029047547,"remaining_time":24.34452672},
{"learn":[0.4146371266],"iteration":142,"passed_time":4.062476163,"remaining_time":24.34644805},
{"learn":[0.4144993724],"iteration":143,"passed_time":4.081927286,"remaining_time":24.26478998},
{"learn":[0.4144222082],"iteration":144,"passed_time":4.107429379,"remaining_time":24.21966979},
{"learn":[0.4143456347],"iteration":145,"passed_time":4.131664466,"remaining_time":24.16740722},
{"learn":[0.4142858751],"iteration":146,"passed_time":4.150541138,"remaining_time":24.08443259},
{"learn":[0.4142267],"iteration":147,"passed_time":4.1767083,"remaining_time":24.04429373},
{"learn":[0.4139979367],"iteration":148,"passed_time":4.202097821,"remaining_time":23.99990097},
{"learn":[0.4138711282],"iteration":149,"passed_time":4.222243354,"remaining_time":23.92604567},
{"learn":[0.4138188924],"iteration":150,"passed_time":4.238745487,"remaining_time":23.83241668},
{"learn":[0.4136772745],"iteration":151,"passed_time":4.260908241,"remaining_time":23.77138282},
{"learn":[0.4133460857],"iteration":152,"passed_time":4.292285119,"remaining_time":23.76186598},
{"learn":[0.413245801],"iteration":153,"passed_time":4.318343404,"remaining_time":23.72284753},
{"learn":[0.4129178779],"iteration":154,"passed_time":4.346367939,"remaining_time":23.69471554},
{"learn":[0.412851579],"iteration":155,"passed_time":4.364062433,"remaining_time":23.61069675},
{"learn":[0.4127796584],"iteration":156,"passed_time":4.389070155,"remaining_time":23.56679071},
{"learn":[0.4124631429],"iteration":157,"passed_time":4.415334074,"remaining_time":23.52981829},
{"learn":[0.4123499767],"iteration":158,"passed_time":4.438903668,"remaining_time":23.47872947},
{"learn":[0.4122964392],"iteration":159,"passed_time":4.459224594,"remaining_time":23.41092912},
{"learn":[0.4121885066],"iteration":160,"passed_time":4.480214508,"remaining_time":23.34720479},
{"learn":[0.4120583561],"iteration":161,"passed_time":4.509321549,"remaining_time":23.32599666},
{"learn":[0.4120153405],"iteration":162,"passed_time":4.532281194,"remaining_time":23.2731249},
{"learn":[0.411769528],"iteration":163,"passed_time":4.55855059,"remaining_time":23.23748959},
{"learn":[0.4117081358],"iteration":164,"passed_time":4.583985493,"remaining_time":23.19774477},
{"learn":[0.4116118985],"iteration":165,"passed_time":4.613628957,"remaining_time":23.17931657},
{"learn":[0.4114154786],"iteration":166,"passed_time":4.640077541,"remaining_time":23.14481791},
{"learn":[0.4113584876],"iteration":167,"passed_time":4.662006172,"remaining_time":23.08803057},
{"learn":[0.4112655065],"iteration":168,"passed_time":4.690548702,"remaining_time":23.06417734},
{"learn":[0.4111697482],"iteration":169,"passed_time":4.710927014,"remaining_time":23.00040836},
{"learn":[0.411006488],"iteration":170,"passed_time":4.732047602,"remaining_time":22.94074539},
{"learn":[0.4109576918],"iteration":171,"passed_time":4.758439824,"remaining_time":22.90690799},
{"learn":[0.4109049884],"iteration":172,"passed_time":4.79896644,"remaining_time":22.94072397},
{"learn":[0.4107141886],"iteration":173,"passed_time":4.845963925,"remaining_time":23.00440346},
{"learn":[0.4106129258],"iteration":174,"passed_time":4.878031688,"remaining_time":22.9964351},
{"learn":[0.4105346773],"iteration":175,"passed_time":4.90514008,"remaining_time":22.96497401},
{"learn":[0.4104866424],"iteration":176,"passed_time":4.939364607,"remaining_time":22.96665012},
{"learn":[0.4104060867],"iteration":177,"passed_time":4.965963408,"remaining_time":22.93270743},
{"learn":[0.4102641647],"iteration":178,"passed_time":4.998972035,"remaining_time":22.92824604},
{"learn":[0.4101756783],"iteration":179,"passed_time":5.025983818,"remaining_time":22.89614851},
{"learn":[0.4100903757],"iteration":180,"passed_time":5.059752026,"remaining_time":22.89467906},
{"learn":[0.4099566017],"iteration":181,"passed_time":5.098951405,"remaining_time":22.91726511},
{"learn":[0.4099011237],"iteration":182,"passed_time":5.125603094,"remaining_time":22.88315698},
{"learn":[0.4097911477],"iteration":183,"passed_time":5.152879654,"remaining_time":22.85190107},
{"learn":[0.4096141554],"iteration":184,"passed_time":5.184441474,"remaining_time":22.83956649},
{"learn":[0.4095666907],"iteration":185,"passed_time":5.204061385,"remaining_time":22.77476327},
{"learn":[0.4092774245],"iteration":186,"passed_time":5.232980224,"remaining_time":22.75087124},
{"learn":[0.4091560106],"iteration":187,"passed_time":5.257757891,"remaining_time":22.7090394},
{"learn":[0.4091152452],"iteration":188,"passed_time":5.287044859,"remaining_time":22.68673747},
{"learn":[0.4088722608],"iteration":189,"passed_time":5.320145736,"remaining_time":22.68062129},
{"learn":[0.4086052524],"iteration":190,"passed_time":5.350860301,"remaining_time":22.6641151},
{"learn":[0.4084915717],"iteration":191,"passed_time":5.380571505,"remaining_time":22.64323842},
{"learn":[0.4084403851],"iteration":192,"passed_time":5.403157913,"remaining_time":22.59247894},
{"learn":[0.408387076],"iteration":193,"passed_time":5.424418928,"remaining_time":22.53650338},
{"learn":[0.408290088],"iteration":194,"passed_time":5.447337061,"remaining_time":22.48772479},
{"learn":[0.408263716],"iteration":195,"passed_time":5.463837202,"remaining_time":22.41288322},
{"learn":[0.4076863878],"iteration":196,"passed_time":5.492798474,"remaining_time":22.38942728},
{"learn":[0.4074883838],"iteration":197,"passed_time":5.517678726,"remaining_time":22.34938555},
{"learn":[0.4074643157],"iteration":198,"passed_time":5.535969149,"remaining_time":22.2829713},
{"learn":[0.4070173186],"iteration":199,"passed_time":5.568855473,"remaining_time":22.27542189},
{"learn":[0.4067920173],"iteration":200,"passed_time":5.598467421,"remaining_time":22.25460433},
{"learn":[0.4067480236],"iteration":201,"passed_time":5.618798782,"remaining_time":22.19703677},
{"learn":[0.4065873827],"iteration":202,"passed_time":5.652534142,"remaining_time":22.19246163},
{"learn":[0.4062667676],"iteration":203,"passed_time":5.686502621,"remaining_time":22.18851023},
{"learn":[0.4059154993],"iteration":204,"passed_time":5.720660729,"remaining_time":22.18500136},
{"learn":[0.4058960761],"iteration":205,"passed_time":5.744632745,"remaining_time":22.14193398},
{"learn":[0.4058696088],"iteration":206,"passed_time":5.764305992,"remaining_time":22.08258286},
{"learn":[0.4057360221],"iteration":207,"passed_time":5.789870882,"remaining_time":22.04604682},
{"learn":[0.4053158286],"iteration":208,"passed_time":5.818924069,"remaining_time":22.02281789},
{"learn":[0.4052667331],"iteration":209,"passed_time":5.842539675,"remaining_time":21.97907782},
{"learn":[0.4045854819],"iteration":210,"passed_time":5.875139461,"remaining_time":21.96912339},
{"learn":[0.4045752059],"iteration":211,"passed_time":5.894015662,"remaining_time":21.90794501},
{"learn":[0.4045553546],"iteration":212,"passed_time":5.917681516,"remaining_time":21.86486081},
{"learn":[0.4042905415],"iteration":213,"passed_time":5.950471443,"remaining_time":21.85546988},
{"learn":[0.4042680149],"iteration":214,"passed_time":5.971460946,"remaining_time":21.80277601},
{"learn":[0.4042144403],"iteration":215,"passed_time":5.996403629,"remaining_time":21.76472428},
{"learn":[0.4042002215],"iteration":216,"passed_time":6.013030675,"remaining_time":21.6967881},
{"learn":[0.4041674035],"iteration":217,"passed_time":6.034549903,"remaining_time":21.64687167},
{"learn":[0.4040324811],"iteration":218,"passed_time":6.061899841,"remaining_time":21.61800811},
{"learn":[0.4039814281],"iteration":219,"passed_time":6.086087146,"remaining_time":21.57794534},
{"learn":[0.4037039605],"iteration":220,"passed_time":6.115175563,"remaining_time":21.5553021},
{"learn":[0.4033173209],"iteration":221,"passed_time":6.14797664,"remaining_time":21.54561183},
{"learn":[0.4031536826],"iteration":222,"passed_time":6.177499918,"remaining_time":21.52429344},
{"learn":[0.4031342962],"iteration":223,"passed_time":6.200715029,"remaining_time":21.48104849},
{"learn":[0.4030029743],"iteration":224,"passed_time":6.232022707,"remaining_time":21.46585599},
{"learn":[0.4029705844],"iteration":225,"passed_time":6.254109361,"remaining_time":21.41894091},
{"learn":[0.4029599538],"iteration":226,"passed_time":6.27667387,"remaining_time":21.37387181},
{"learn":[0.4029496262],"iteration":227,"passed_time":6.291165359,"remaining_time":21.30166516},
{"learn":[0.4028788867],"iteration":228,"passed_time":6.313560992,"remaining_time":21.25657434},
{"learn":[0.4028145711],"iteration":229,"passed_time":6.335915228,"remaining_time":21.21154228},
{"learn":[0.4028051734],"iteration":230,"passed_time":6.355264293,"remaining_time":21.15670234},
{"learn":[0.4027960301],"iteration":231,"passed_time":6.37434796,"remaining_time":21.1012898},
{"learn":[0.4027460965],"iteration":232,"passed_time":6.393434934,"remaining_time":21.04619998},
{"learn":[0.4027100044],"iteration":233,"passed_time":6.413146927,"remaining_time":20.99346387},
{"learn":[0.4026440744],"iteration":234,"passed_time":6.441995173,"remaining_time":20.97075025},
{"learn":[0.4026357799],"iteration":235,"passed_time":6.465063044,"remaining_time":20.92927189},
{"learn":[0.4025797681],"iteration":236,"passed_time":6.493091756,"remaining_time":20.90391987},
{"learn":[0.4025696019],"iteration":237,"passed_time":6.516035367,"remaining_time":20.86226449},
{"learn":[0.4018505836],"iteration":238,"passed_time":6.558663757,"remaining_time":20.88344401},
{"learn":[0.4018278817],"iteration":239,"passed_time":6.581156944,"remaining_time":20.84033032},
{"learn":[0.401134768],"iteration":240,"passed_time":6.614313717,"remaining_time":20.83097142},
{"learn":[0.401096544],"iteration":241,"passed_time":6.643923613,"remaining_time":20.81030619},
{"learn":[0.4010507521],"iteration":242,"passed_time":6.669405999,"remaining_time":20.77670922},
{"learn":[0.4009743522],"iteration":243,"passed_time":6.695337929,"remaining_time":20.74457162},
{"learn":[0.4008519587],"iteration":244,"passed_time":6.723824722,"remaining_time":20.72035782},
{"learn":[0.4006232878],"iteration":245,"passed_time":6.760935742,"remaining_time":20.72254288},
{"learn":[0.4005384719],"iteration":246,"passed_time":6.785590256,"remaining_time":20.68643507},
{"learn":[0.4005048222],"iteration":247,"passed_time":6.804604983,"remaining_time":20.63331834},
{"learn":[0.4002264894],"iteration":248,"passed_time":6.835478668,"remaining_time":20.61624289},
{"learn":[0.4002204302],"iteration":249,"passed_time":6.85255285,"remaining_time":20.55765855},
{"learn":[0.4001888819],"iteration":250,"passed_time":6.879485012,"remaining_time":20.52882181},
{"learn":[0.4000938495],"iteration":251,"passed_time":6.904049477,"remaining_time":20.49297226},
{"learn":[0.4000734115],"iteration":252,"passed_time":6.928581654,"remaining_time":20.45711658},
{"learn":[0.4000143184],"iteration":253,"passed_time":6.95160676,"remaining_time":20.41692379},
{"learn":[0.4000090419],"iteration":254,"passed_time":6.972102708,"remaining_time":20.36947654},
{"learn":[0.3999316777],"iteration":255,"passed_time":6.992421179,"remaining_time":20.32172405},
{"learn":[0.3999033653],"iteration":256,"passed_time":7.026891472,"remaining_time":20.31509869},
{"learn":[0.3998128296],"iteration":257,"passed_time":7.060638263,"remaining_time":20.30617671},
{"learn":[0.3997988591],"iteration":258,"passed_time":7.075593619,"remaining_time":20.24330066},
{"learn":[0.3997961753],"iteration":259,"passed_time":7.09284138,"remaining_time":20.18731777},
{"learn":[0.399740369],"iteration":260,"passed_time":7.121141599,"remaining_time":20.16292583},
{"learn":[0.3992909524],"iteration":261,"passed_time":7.157714822,"remaining_time":20.1618074},
{"learn":[0.3992884123],"iteration":262,"passed_time":7.173276275,"remaining_time":20.10153846},
{"learn":[0.3992373211],"iteration":263,"passed_time":7.197537777,"remaining_time":20.06586289},
{"learn":[0.399223949],"iteration":264,"passed_time":7.225496528,"remaining_time":20.04052811},
{"learn":[0.3990559579],"iteration":265,"passed_time":7.260602494,"remaining_time":20.0348956},
{"learn":[0.398962826],"iteration":266,"passed_time":7.288082847,"remaining_time":20.00810759},
{"learn":[0.3989589114],"iteration":267,"passed_time":7.307052153,"remaining_time":19.95806782},
{"learn":[0.3989166136],"iteration":268,"passed_time":7.342199361,"remaining_time":19.95222206},
{"learn":[0.3988163907],"iteration":269,"passed_time":7.371898144,"remaining_time":19.93142831},
{"learn":[0.3988144123],"iteration":270,"passed_time":7.390334314,"remaining_time":19.88027201},
{"learn":[0.3987956448],"iteration":271,"passed_time":7.419602149,"remaining_time":19.85834693},
{"learn":[0.3987897635],"iteration":272,"passed_time":7.437983992,"remaining_time":19.80737862},
{"learn":[0.3987733107],"iteration":273,"passed_time":7.465982146,"remaining_time":19.78212788},
{"learn":[0.3987607527],"iteration":274,"passed_time":7.506301912,"remaining_time":19.7893414},
{"learn":[0.398757286],"iteration":275,"passed_time":7.525724624,"remaining_time":19.74139358},
{"learn":[0.3987425035],"iteration":276,"passed_time":7.554183104,"remaining_time":19.71723605},
{"learn":[0.3986666665],"iteration":277,"passed_time":7.588517148,"remaining_time":19.70830713},
{"learn":[0.3986634952],"iteration":278,"passed_time":7.605772902,"remaining_time":19.65506187},
{"learn":[0.398641589],"iteration":279,"passed_time":7.634128523,"remaining_time":19.6306162},
{"learn":[0.3986246657],"iteration":280,"passed_time":7.65578765,"remaining_time":19.58900826},
{"learn":[0.398617797],"iteration":281,"passed_time":7.682842278,"remaining_time":19.56127928},
{"learn":[0.3986148205],"iteration":282,"passed_time":7.697328998,"remaining_time":19.5017134},
{"learn":[0.3986064256],"iteration":283,"passed_time":7.720149611,"remaining_time":19.46347578},
{"learn":[0.3986036275],"iteration":284,"passed_time":7.734792844,"remaining_time":19.40483117},
{"learn":[0.3985380463],"iteration":285,"passed_time":7.770414612,"remaining_time":19.39886725},
{"learn":[0.3985272434],"iteration":286,"passed_time":7.799754274,"remaining_time":19.37708989},
{"learn":[0.3985204238],"iteration":287,"passed_time":7.828167945,"remaining_time":19.35297075},
{"learn":[0.39846526],"iteration":288,"passed_time":7.862546976,"remaining_time":19.34349792},
{"learn":[0.3984217965],"iteration":289,"passed_time":7.894229024,"remaining_time":19.32725037},
{"learn":[0.3983525281],"iteration":290,"passed_time":7.925727678,"remaining_time":19.31044991},
{"learn":[0.3983496787],"iteration":291,"passed_time":7.947392033,"remaining_time":19.26970397},
{"learn":[0.3982031428],"iteration":292,"passed_time":7.981865602,"remaining_time":19.25999652},
{"learn":[0.3981915852],"iteration":293,"passed_time":8.006452753,"remaining_time":19.22637974},
{"learn":[0.3981566721],"iteration":294,"passed_time":8.035955806,"remaining_time":19.20457235},
{"learn":[0.3981492355],"iteration":295,"passed_time":8.060008661,"remaining_time":19.16975033},
{"learn":[0.3981467493],"iteration":296,"passed_time":8.084906509,"remaining_time":19.13700093},
{"learn":[0.3981239441],"iteration":297,"passed_time":8.119592384,"remaining_time":19.12736192},
{"learn":[0.3981027018],"iteration":298,"passed_time":8.137614365,"remaining_time":19.07848719},
{"learn":[0.3980959834],"iteration":299,"passed_time":8.16029233,"remaining_time":19.0406821},
{"learn":[0.3980894078],"iteration":300,"passed_time":8.184431077,"remaining_time":19.00636984},
{"learn":[0.3980877451],"iteration":301,"passed_time":8.202975053,"remaining_time":18.959194},
{"learn":[0.3980277201],"iteration":302,"passed_time":8.233981798,"remaining_time":18.94087562},
{"learn":[0.3980105449],"iteration":303,"passed_time":8.27050573,"remaining_time":18.93510522},
{"learn":[0.3976612079],"iteration":304,"passed_time":8.308499211,"remaining_time":18.93248181},
{"learn":[0.3975908551],"iteration":305,"passed_time":8.343108211,"remaining_time":18.9219513},
{"learn":[0.3975738871],"iteration":306,"passed_time":8.363666039,"remaining_time":18.87954581},
{"learn":[0.3975599723],"iteration":307,"passed_time":8.387375993,"remaining_time":18.84436424},
{"learn":[0.3974680587],"iteration":308,"passed_time":8.41533287,"remaining_time":18.81875409},
{"learn":[0.3974638027],"iteration":309,"passed_time":8.433934875,"remaining_time":18.77230666},
{"learn":[0.3974624085],"iteration":310,"passed_time":8.453276138,"remaining_time":18.72767608},
{"learn":[0.397443797],"iteration":311,"passed_time":8.481662361,"remaining_time":18.7031529},
{"learn":[0.3974398165],"iteration":312,"passed_time":8.512219594,"remaining_time":18.68337016},
{"learn":[0.3974217231],"iteration":313,"passed_time":8.546581143,"remaining_time":18.67183014},
{"learn":[0.3974159745],"iteration":314,"passed_time":8.569093004,"remaining_time":18.63437685},
{"learn":[0.397362958],"iteration":315,"passed_time":8.611724829,"remaining_time":18.64056893},
{"learn":[0.39727717],"iteration":316,"passed_time":8.648013537,"remaining_time":18.63278626},
{"learn":[0.3970773251],"iteration":317,"passed_time":8.691147723,"remaining_time":18.63950549},
{"learn":[0.3970761635],"iteration":318,"passed_time":8.710540602,"remaining_time":18.59522931},
{"learn":[0.3969858108],"iteration":319,"passed_time":8.736034047,"remaining_time":18.56407235},
{"learn":[0.3969847333],"iteration":320,"passed_time":8.753994229,"remaining_time":18.51701583},
{"learn":[0.396659875],"iteration":321,"passed_time":8.793888404,"remaining_time":18.51632403},
{"learn":[0.3964209187],"iteration":322,"passed_time":8.831882287,"remaining_time":18.51140653},
{"learn":[0.3963909073],"iteration":323,"passed_time":8.854862388,"remaining_time":18.4749598},
{"learn":[0.3963208856],"iteration":324,"passed_time":8.882218143,"remaining_time":18.44768384},
{"learn":[0.396313393],"iteration":325,"passed_time":8.910610782,"remaining_time":18.42255113},
{"learn":[0.3962837258],"iteration":326,"passed_time":8.946814101,"remaining_time":18.41347367},
{"learn":[0.39627635],"iteration":327,"passed_time":8.967784713,"remaining_time":18.37302234},
{"learn":[0.396265173],"iteration":328,"passed_time":8.989580952,"remaining_time":18.33437331},
{"learn":[0.3962592792],"iteration":329,"passed_time":9.01284213,"remaining_time":18.29880069},
{"learn":[0.3960985676],"iteration":330,"passed_time":9.047763699,"remaining_time":18.28686983},
{"learn":[0.3960954452],"iteration":331,"passed_time":9.06298999,"remaining_time":18.23517263},
{"learn":[0.3960923794],"iteration":332,"passed_time":9.080746753,"remaining_time":18.18876302},
{"learn":[0.396089408],"iteration":333,"passed_time":9.099695148,"remaining_time":18.1449011},
{"learn":[0.3960601119],"iteration":334,"passed_time":9.126773,"remaining_time":18.11732551},
{"learn":[0.3960533052],"iteration":335,"passed_time":9.148514128,"remaining_time":18.07920649},
{"learn":[0.3960392501],"iteration":336,"passed_time":9.181838631,"remaining_time":18.06397333},
{"learn":[0.3959266782],"iteration":337,"passed_time":9.214836885,"remaining_time":18.04799414},
{"learn":[0.3959222793],"iteration":338,"passed_time":9.23450362,"remaining_time":18.00592004},
{"learn":[0.3958945135],"iteration":339,"passed_time":9.26521238,"remaining_time":17.98541227},
{"learn":[0.3958810267],"iteration":340,"passed_time":9.293033166,"remaining_time":17.95926351},
{"learn":[0.3956749484],"iteration":341,"passed_time":9.323234051,"remaining_time":17.93768423},
{"learn":[0.3956651118],"iteration":342,"passed_time":9.338560738,"remaining_time":17.88756386},
{"learn":[0.3956343852],"iteration":343,"passed_time":9.365005806,"remaining_time":17.85884828},
{"learn":[0.3956338027],"iteration":344,"passed_time":9.37947539,"remaining_time":17.8074098},
{"learn":[0.3956027869],"iteration":345,"passed_time":9.399454885,"remaining_time":17.7665997},
{"learn":[0.3955726277],"iteration":346,"passed_time":9.420375372,"remaining_time":17.72768045},
{"learn":[0.3955462537],"iteration":347,"passed_time":9.443272103,"remaining_time":17.69256727},
{"learn":[0.395542188],"iteration":348,"passed_time":9.463548769,"remaining_time":17.65263682},
{"learn":[0.3955327334],"iteration":349,"passed_time":9.488068176,"remaining_time":17.62069804},
{"learn":[0.3955194552],"iteration":350,"passed_time":9.507490532,"remaining_time":17.57937708},
{"learn":[0.3955189288],"iteration":351,"passed_time":9.522225549,"remaining_time":17.52955158},
{"learn":[0.395508053],"iteration":352,"passed_time":9.545678951,"remaining_time":17.49590448},
{"learn":[0.3954960462],"iteration":353,"passed_time":9.573576278,"remaining_time":17.47042451},
{"learn":[0.3954711419],"iteration":354,"passed_time":9.599166146,"remaining_time":17.44073849},
{"learn":[0.395470678],"iteration":355,"passed_time":9.613723148,"remaining_time":17.39111716},
{"learn":[0.3954440031],"iteration":356,"passed_time":9.637308723,"remaining_time":17.35795381},
{"learn":[0.3950746079],"iteration":357,"passed_time":9.667158395,"remaining_time":17.33607735},
{"learn":[0.3947686456],"iteration":358,"passed_time":9.699280854,"remaining_time":17.31821456},
{"learn":[0.3947439289],"iteration":359,"passed_time":9.723906372,"remaining_time":17.28694466},
{"learn":[0.3947191594],"iteration":360,"passed_time":9.748180085,"remaining_time":17.25508885},
{"learn":[0.3947080793],"iteration":361,"passed_time":9.77811719,"remaining_time":17.23325626},
{"learn":[0.3946841111],"iteration":362,"passed_time":9.79918598,"remaining_time":17.19581672},
{"learn":[0.3945510175],"iteration":363,"passed_time":9.822723626,"remaining_time":17.16278084},
{"learn":[0.3945381599],"iteration":364,"passed_time":9.846805394,"remaining_time":17.13074363},
{"learn":[0.3944093417],"iteration":365,"passed_time":9.877248157,"remaining_time":17.10976867},
{"learn":[0.3944090385],"iteration":366,"passed_time":9.890043173,"remaining_time":17.05830335},
{"learn":[0.3942669195],"iteration":367,"passed_time":9.919811812,"remaining_time":17.03619855},
{"learn":[0.3942608312],"iteration":368,"passed_time":9.939260544,"remaining_time":16.99640489},
{"learn":[0.3942605593],"iteration":369,"passed_time":9.953877871,"remaining_time":16.94849475},
{"learn":[0.3942552031],"iteration":370,"passed_time":9.984380495,"remaining_time":16.92769631},
{"learn":[0.3942279799],"iteration":371,"passed_time":10.00967635,"remaining_time":16.89805578},
{"learn":[0.3942277367],"iteration":372,"passed_time":10.0239068,"remaining_time":16.84983797},
{"learn":[0.3942021982],"iteration":373,"passed_time":10.05307897,"remaining_time":16.82681132},
{"learn":[0.3941973454],"iteration":374,"passed_time":10.07824519,"remaining_time":16.79707532},
{"learn":[0.3941970963],"iteration":375,"passed_time":10.09342339,"remaining_time":16.75078775},
{"learn":[0.3941857084],"iteration":376,"passed_time":10.1198139,"remaining_time":16.7231938},
{"learn":[0.3941839067],"iteration":377,"passed_time":10.14243712,"remaining_time":16.6894071},
{"learn":[0.3936920156],"iteration":378,"passed_time":10.17675519,"remaining_time":16.67484161},
{"learn":[0.3936863331],"iteration":379,"passed_time":10.20127654,"remaining_time":16.64418804},
{"learn":[0.3936814204],"iteration":380,"passed_time":10.22041478,"remaining_time":16.60482086},
{"learn":[0.3936740431],"iteration":381,"passed_time":10.23699115,"remaining_time":16.561415},
{"learn":[0.3935606573],"iteration":382,"passed_time":10.27113054,"remaining_time":16.54644267},
{"learn":[0.3935588946],"iteration":383,"passed_time":10.28634161,"remaining_time":16.50100633},
{"learn":[0.393535053],"iteration":384,"passed_time":10.31109553,"remaining_time":16.47097079},
{"learn":[0.3935141835],"iteration":385,"passed_time":10.33587708,"remaining_time":16.44100654},
{"learn":[0.3935139984],"iteration":386,"passed_time":10.35025937,"remaining_time":16.39459689},
{"learn":[0.3934926188],"iteration":387,"passed_time":10.37989493,"remaining_time":16.37241159},
{"learn":[0.3934924534],"iteration":388,"passed_time":10.39679692,"remaining_time":16.33018745},
{"learn":[0.3934693469],"iteration":389,"passed_time":10.41765222,"remaining_time":16.29427655},
{"learn":[0.3934691821],"iteration":390,"passed_time":10.431731,"remaining_time":16.24788792},
{"learn":[0.3934685918],"iteration":391,"passed_time":10.45112814,"remaining_time":16.20991303},
{"learn":[0.3934684369],"iteration":392,"passed_time":10.46553479,"remaining_time":16.16432472},
{"learn":[0.3934637534],"iteration":393,"passed_time":10.48671938,"remaining_time":16.12931966},
{"learn":[0.393434646],"iteration":394,"passed_time":10.51163599,"remaining_time":16.1001007},
{"learn":[0.3934309537],"iteration":395,"passed_time":10.53715541,"remaining_time":16.0718229},
{"learn":[0.3934294187],"iteration":396,"passed_time":10.55928954,"remaining_time":16.0384171},
{"learn":[0.3934226392],"iteration":397,"passed_time":10.57815739,"remaining_time":16.0001275},
{"learn":[0.3933347325],"iteration":398,"passed_time":10.60893502,"remaining_time":15.97987456},
{"learn":[0.3933122643],"iteration":399,"passed_time":10.63156707,"remaining_time":15.9473506},
{"learn":[0.3931973382],"iteration":400,"passed_time":10.67430044,"remaining_time":15.94490264},
{"learn":[0.3931959107],"iteration":401,"passed_time":10.69269345,"remaining_time":15.90604647},
{"learn":[0.3931120472],"iteration":402,"passed_time":10.72051603,"remaining_time":15.88126072},
{"learn":[0.3930615188],"iteration":403,"passed_time":10.74114039,"remaining_time":15.84584077},
{"learn":[0.3930077672],"iteration":404,"passed_time":10.76401786,"remaining_time":15.81380401},
{"learn":[0.3928889568],"iteration":405,"passed_time":10.79632344,"remaining_time":15.79560622},
{"learn":[0.39286982],"iteration":406,"passed_time":10.82145158,"remaining_time":15.76688154},
{"learn":[0.3928637931],"iteration":407,"passed_time":10.83801786,"remaining_time":15.72575141},
{"learn":[0.3928624309],"iteration":408,"passed_time":10.85887563,"remaining_time":15.69094254},
{"learn":[0.3928593989],"iteration":409,"passed_time":10.88028503,"remaining_time":15.65699553},
{"learn":[0.3928509905],"iteration":410,"passed_time":10.90603706,"remaining_time":15.62933292},
{"learn":[0.3928399448],"iteration":411,"passed_time":10.93505346,"remaining_time":15.60633844},
{"learn":[0.3928398403],"iteration":412,"passed_time":10.95333073,"remaining_time":15.56805119},
{"learn":[0.3926888746],"iteration":413,"passed_time":10.99276291,"remaining_time":15.55980451},
{"learn":[0.3926682357],"iteration":414,"passed_time":11.01861904,"remaining_time":15.53227021},
{"learn":[0.3926509349],"iteration":415,"passed_time":11.05640062,"remaining_time":15.52148549},
{"learn":[0.392540896],"iteration":416,"passed_time":11.09680557,"remaining_time":15.51423897},
{"learn":[0.3925367912],"iteration":417,"passed_time":11.12354346,"remaining_time":15.48780453},
{"learn":[0.3925327666],"iteration":418,"passed_time":11.14746031,"remaining_time":15.45745689},
{"learn":[0.3925300082],"iteration":419,"passed_time":11.18252011,"remaining_time":15.44252777},
{"learn":[0.39252843],"iteration":420,"passed_time":11.20797671,"remaining_time":15.41429576},
{"learn":[0.3925116127],"iteration":421,"passed_time":11.24375184,"remaining_time":15.40020987},
{"learn":[0.3925112398],"iteration":422,"passed_time":11.26946686,"remaining_time":15.37229877},
{"learn":[0.3924925615],"iteration":423,"passed_time":11.29780572,"remaining_time":15.34796248},
{"learn":[0.3924303006],"iteration":424,"passed_time":11.32834914,"remaining_time":15.32659001},
{"learn":[0.3924291254],"iteration":425,"passed_time":11.35764854,"remaining_time":15.30349826},
{"learn":[0.3924205833],"iteration":426,"passed_time":11.38368381,"remaining_time":15.27599724},
{"learn":[0.3924079183],"iteration":427,"passed_time":11.4031982,"remaining_time":15.23978825},
{"learn":[0.3923981804],"iteration":428,"passed_time":11.435723,"remaining_time":15.22097397},
{"learn":[0.3923690829],"iteration":429,"passed_time":11.46429221,"remaining_time":15.19685246},
{"learn":[0.3923380991],"iteration":430,"passed_time":11.49407634,"remaining_time":15.17431424},
{"learn":[0.3922332183],"iteration":431,"passed_time":11.52767612,"remaining_time":15.15675935},
{"learn":[0.3922322038],"iteration":432,"passed_time":11.5448757,"remaining_time":15.11765478},
{"learn":[0.3922321453],"iteration":433,"passed_time":11.56190945,"remaining_time":15.0784349},
{"learn":[0.3922320886],"iteration":434,"passed_time":11.57582319,"remaining_time":15.03526461},
{"learn":[0.3922282759],"iteration":435,"passed_time":11.59950083,"remaining_time":15.00485888},
{"learn":[0.3922222176],"iteration":436,"passed_time":11.62292096,"remaining_time":14.97415217},
{"learn":[0.3922113221],"iteration":437,"passed_time":11.64451352,"remaining_time":14.94113379},
{"learn":[0.3922022354],"iteration":438,"passed_time":11.66989759,"remaining_time":14.91301263},
{"learn":[0.3920053445],"iteration":439,"passed_time":11.69404347,"remaining_time":14.88332805},
{"learn":[0.3919985201],"iteration":440,"passed_time":11.71109099,"remaining_time":14.84467089},
{"learn":[0.391957092],"iteration":441,"passed_time":11.74411496,"remaining_time":14.82628087},
{"learn":[0.3918495312],"iteration":442,"passed_time":11.77536338,"remaining_time":14.80559233},
{"learn":[0.3918458896],"iteration":443,"passed_time":11.79333842,"remaining_time":14.7682346},
{"learn":[0.3918370977],"iteration":444,"passed_time":11.81341145,"remaining_time":14.73358057},
{"learn":[0.3916274274],"iteration":445,"passed_time":11.83834564,"remaining_time":14.70503024},
{"learn":[0.3916239794],"iteration":446,"passed_time":11.85625525,"remaining_time":14.66780571},
{"learn":[0.3916239343],"iteration":447,"passed_time":11.86929807,"remaining_time":14.62467084},
{"learn":[0.3916229743],"iteration":448,"passed_time":11.88616758,"remaining_time":14.586366},
{"learn":[0.391608183],"iteration":449,"passed_time":11.91921253,"remaining_time":14.56792643},
{"learn":[0.3915754045],"iteration":450,"passed_time":11.94966444,"remaining_time":14.54626558},
{"learn":[0.391572037],"iteration":451,"passed_time":11.96968171,"remaining_time":14.51191499},
{"learn":[0.3915563628],"iteration":452,"passed_time":11.99062107,"remaining_time":14.47874111},
{"learn":[0.3915555215],"iteration":453,"passed_time":12.00396209,"remaining_time":14.43648304},
{"learn":[0.391555215],"iteration":454,"passed_time":12.02332112,"remaining_time":14.40156047},
{"learn":[0.3915373301],"iteration":455,"passed_time":12.04356752,"remaining_time":14.36776476},
{"learn":[0.3915350879],"iteration":456,"passed_time":12.06125255,"remaining_time":14.33098497},
{"learn":[0.39152691],"iteration":457,"passed_time":12.08241497,"remaining_time":14.29840374},
{"learn":[0.3915260347],"iteration":458,"passed_time":12.1024942,"remaining_time":14.26459556},
{"learn":[0.3915260032],"iteration":459,"passed_time":12.11968006,"remaining_time":14.2274505},
{"learn":[0.3915242208],"iteration":460,"passed_time":12.13757051,"remaining_time":14.19121585},
{"learn":[0.3915169611],"iteration":461,"passed_time":12.16331148,"remaining_time":14.16420255},
{"learn":[0.391516927],"iteration":462,"passed_time":12.17982768,"remaining_time":14.12649561},
{"learn":[0.3915137605],"iteration":463,"passed_time":12.20021929,"remaining_time":14.09335677},
{"learn":[0.3912701281],"iteration":464,"passed_time":12.22610204,"remaining_time":14.06659052},
{"learn":[0.3911863597],"iteration":465,"passed_time":12.25308022,"remaining_time":14.04108335},
{"learn":[0.3911855084],"iteration":466,"passed_time":12.26996848,"remaining_time":14.00405396},
{"learn":[0.3911854816],"iteration":467,"passed_time":12.28298135,"remaining_time":13.96270529},
{"learn":[0.3911670159],"iteration":468,"passed_time":12.32195683,"remaining_time":13.95087223},
{"learn":[0.3911669913],"iteration":469,"passed_time":12.33856469,"remaining_time":13.91370061},
{"learn":[0.3911669674],"iteration":470,"passed_time":12.353818,"remaining_time":13.87509495},
{"learn":[0.3911520688],"iteration":471,"passed_time":12.37841097,"remaining_time":13.847036},
{"learn":[0.3911375585],"iteration":472,"passed_time":12.4011954,"remaining_time":13.81697669},
{"learn":[0.391131214],"iteration":473,"passed_time":12.41895507,"remaining_time":13.78137208},
{"learn":[0.3911309661],"iteration":474,"passed_time":12.43477774,"remaining_time":13.74370171},
{"learn":[0.391111928],"iteration":475,"passed_time":12.45672055,"remaining_time":13.71286044},
{"learn":[0.3910977686],"iteration":476,"passed_time":12.48042757,"remaining_time":13.68399081},
{"learn":[0.3910960842],"iteration":477,"passed_time":12.49865303,"remaining_time":13.64915665},
{"learn":[0.3910960627],"iteration":478,"passed_time":12.51268142,"remaining_time":13.60982676},
{"learn":[0.3910849567],"iteration":479,"passed_time":12.53989966,"remaining_time":13.5848913},
{"learn":[0.3910849368],"iteration":480,"passed_time":12.55391027,"remaining_time":13.54569528},
{"learn":[0.3910841808],"iteration":481,"passed_time":12.57434641,"remaining_time":13.51350922},
{"learn":[0.3909794063],"iteration":482,"passed_time":12.60921298,"remaining_time":13.49681803},
{"learn":[0.3909774198],"iteration":483,"passed_time":12.62629512,"remaining_time":13.46109149},
{"learn":[0.3907800927],"iteration":484,"passed_time":12.65488986,"remaining_time":13.43766655},
{"learn":[0.3907781018],"iteration":485,"passed_time":12.67817029,"remaining_time":13.40859985},
{"learn":[0.3907780842],"iteration":486,"passed_time":12.69277979,"remaining_time":13.37042306},
{"learn":[0.3907613767],"iteration":487,"passed_time":12.71922143,"remaining_time":13.34475691},
{"learn":[0.3906603391],"iteration":488,"passed_time":12.7498277,"remaining_time":13.32343958},
{"learn":[0.3904200359],"iteration":489,"passed_time":12.77559042,"remaining_time":13.29704309},
{"learn":[0.3904066325],"iteration":490,"passed_time":12.79567972,"remaining_time":13.26476778},
{"learn":[0.3903908189],"iteration":491,"passed_time":12.81517563,"remaining_time":13.23192931},
{"learn":[0.3903901429],"iteration":492,"passed_time":12.83433517,"remaining_time":13.19879905},
{"learn":[0.3903724508],"iteration":493,"passed_time":12.8650178,"remaining_time":13.17752835},
{"learn":[0.3903596597],"iteration":494,"passed_time":12.90166588,"remaining_time":13.16230559},
{"learn":[0.3903596463],"iteration":495,"passed_time":12.91819903,"remaining_time":13.12655708},
{"learn":[0.3903577431],"iteration":496,"passed_time":12.94014999,"remaining_time":13.0963691},
{"learn":[0.3903505273],"iteration":497,"passed_time":12.96348839,"remaining_time":13.0676128},
{"learn":[0.3903437957],"iteration":498,"passed_time":12.98409729,"remaining_time":13.03613776},
{"learn":[0.3903313685],"iteration":499,"passed_time":13.01475128,"remaining_time":13.01475128},
{"learn":[0.3903313563],"iteration":500,"passed_time":13.0290376,"remaining_time":12.97702547},
{"learn":[0.3903313503],"iteration":501,"passed_time":13.04390088,"remaining_time":12.93996541},
{"learn":[0.3903313387],"iteration":502,"passed_time":13.05946642,"remaining_time":12.9036875},
{"learn":[0.390330686],"iteration":503,"passed_time":13.0812074,"remaining_time":12.87356919},
{"learn":[0.3903279206],"iteration":504,"passed_time":13.10186882,"remaining_time":12.84242587},
{"learn":[0.3903279206],"iteration":505,"passed_time":13.11631376,"remaining_time":12.80525494},
{"learn":[0.390288917],"iteration":506,"passed_time":13.13429413,"remaining_time":12.77161145},
{"learn":[0.3902863263],"iteration":507,"passed_time":13.15787642,"remaining_time":12.74345512},
{"learn":[0.3901943845],"iteration":508,"passed_time":13.18046578,"remaining_time":12.71435894},
{"learn":[0.3901747622],"iteration":509,"passed_time":13.20530015,"remaining_time":12.68744524},
{"learn":[0.3901747511],"iteration":510,"passed_time":13.22316338,"remaining_time":12.65386868},
{"learn":[0.390170194],"iteration":511,"passed_time":13.24134137,"remaining_time":12.62065349},
{"learn":[0.3901701822],"iteration":512,"passed_time":13.25556418,"remaining_time":12.58374221},
{"learn":[0.3901487682],"iteration":513,"passed_time":13.28591922,"remaining_time":12.56217265},
{"learn":[0.3901374352],"iteration":514,"passed_time":13.31082885,"remaining_time":12.53544077},
{"learn":[0.3899632],"iteration":515,"passed_time":13.33705677,"remaining_time":12.50995247},
{"learn":[0.3899614308],"iteration":516,"passed_time":13.35427066,"remaining_time":12.47604009},
{"learn":[0.3899600429],"iteration":517,"passed_time":13.37005371,"remaining_time":12.44086079},
{"learn":[0.3896692768],"iteration":518,"passed_time":13.39613943,"remaining_time":12.41530456},
{"learn":[0.3896679685],"iteration":519,"passed_time":13.42018211,"remaining_time":12.38786041},
{"learn":[0.3896679609],"iteration":520,"passed_time":13.43526017,"remaining_time":12.35218738},
{"learn":[0.3896579206],"iteration":521,"passed_time":13.46592269,"remaining_time":12.33086408},
{"learn":[0.3896569034],"iteration":522,"passed_time":13.49339743,"remaining_time":12.30659766},
{"learn":[0.3894912264],"iteration":523,"passed_time":13.51694753,"remaining_time":12.27875387},
{"learn":[0.3894910467],"iteration":524,"passed_time":13.53139854,"remaining_time":12.24269392},
{"learn":[0.389465713],"iteration":525,"passed_time":13.55385237,"remaining_time":12.2139278},
{"learn":[0.3894651503],"iteration":526,"passed_time":13.57036278,"remaining_time":12.17985122},
{"learn":[0.3894543336],"iteration":527,"passed_time":13.59958212,"remaining_time":12.1572022},
{"learn":[0.3894537846],"iteration":528,"passed_time":13.62211126,"remaining_time":12.12857165},
{"learn":[0.3894468026],"iteration":529,"passed_time":13.64169797,"remaining_time":12.09735481},
{"learn":[0.3894451994],"iteration":530,"passed_time":13.6647345,"remaining_time":12.06922877},
{"learn":[0.3894451928],"iteration":531,"passed_time":13.67874283,"remaining_time":12.03317979},
{"learn":[0.3894451865],"iteration":532,"passed_time":13.6914693,"remaining_time":11.99609036},
{"learn":[0.3894359148],"iteration":533,"passed_time":13.71274661,"remaining_time":11.96655416},
{"learn":[0.3894342565],"iteration":534,"passed_time":13.7299162,"remaining_time":11.93347856},
{"learn":[0.3894329282],"iteration":535,"passed_time":13.74637376,"remaining_time":11.89984595},
{"learn":[0.3894329205],"iteration":536,"passed_time":13.75925741,"remaining_time":11.86319587},
{"learn":[0.3894312794],"iteration":537,"passed_time":13.77683904,"remaining_time":11.83066847},
{"learn":[0.3894153548],"iteration":538,"passed_time":13.81041529,"remaining_time":11.81187653},
{"learn":[0.3893995656],"iteration":539,"passed_time":13.83944138,"remaining_time":11.78915377},
{"learn":[0.3893873729],"iteration":540,"passed_time":13.86463124,"remaining_time":11.76315294},
{"learn":[0.3893850515],"iteration":541,"passed_time":13.88677365,"remaining_time":11.73457995},
{"learn":[0.3893845467],"iteration":542,"passed_time":13.90489274,"remaining_time":11.70264453},
{"learn":[0.3893671126],"iteration":543,"passed_time":13.93016518,"remaining_time":11.6767561},
{"learn":[0.3893652192],"iteration":544,"passed_time":13.95036045,"remaining_time":11.6466312},
{"learn":[0.3893601921],"iteration":545,"passed_time":13.97807931,"remaining_time":11.62279855},
{"learn":[0.3893579679],"iteration":546,"passed_time":14.00057278,"remaining_time":11.59462426},
{"learn":[0.3893557814],"iteration":547,"passed_time":14.0217127,"remaining_time":11.56535427},
{"learn":[0.3893557788],"iteration":548,"passed_time":14.03562268,"remaining_time":11.53017455},
{"learn":[0.3893557736],"iteration":549,"passed_time":14.0510946,"remaining_time":11.49635013},
{"learn":[0.3893505503],"iteration":550,"passed_time":14.07558878,"remaining_time":11.4699444},
{"learn":[0.3893487129],"iteration":551,"passed_time":14.09751499,"remaining_time":11.44146144},
{"learn":[0.3893329498],"iteration":552,"passed_time":14.12004407,"remaining_time":11.41348951},
{"learn":[0.3893324863],"iteration":553,"passed_time":14.13732494,"remaining_time":11.38131213},
{"learn":[0.3893324817],"iteration":554,"passed_time":14.14954665,"remaining_time":11.345132},
{"learn":[0.389327786],"iteration":555,"passed_time":14.16947797,"remaining_time":11.31519464},
{"learn":[0.3893182688],"iteration":556,"passed_time":14.20041468,"remaining_time":11.29404614},
{"learn":[0.3893178261],"iteration":557,"passed_time":14.22202086,"remaining_time":11.26547172},
{"learn":[0.3893173864],"iteration":558,"passed_time":14.24388378,"remaining_time":11.23712477},
{"learn":[0.3893172233],"iteration":559,"passed_time":14.26502213,"remaining_time":11.20823168},
{"learn":[0.3893150166],"iteration":560,"passed_time":14.28443768,"remaining_time":11.17801808},
{"learn":[0.3893057793],"iteration":561,"passed_time":14.30965685,"remaining_time":11.15236601},
{"learn":[0.3893037395],"iteration":562,"passed_time":14.33367521,"remaining_time":11.12578342},
{"learn":[0.3892989004],"iteration":563,"passed_time":14.37117112,"remaining_time":11.10962874},
{"learn":[0.3892914876],"iteration":564,"passed_time":14.39813744,"remaining_time":11.08529165},
{"learn":[0.3892825155],"iteration":565,"passed_time":14.4244458,"remaining_time":11.06044077},
{"learn":[0.3892821071],"iteration":566,"passed_time":14.44323787,"remaining_time":11.02984479},
{"learn":[0.3892650738],"iteration":567,"passed_time":14.47143237,"remaining_time":11.00644152},
{"learn":[0.3892565471],"iteration":568,"passed_time":14.49838081,"remaining_time":10.98207756},
{"learn":[0.3892453378],"iteration":569,"passed_time":14.51855194,"remaining_time":10.95259181},
{"learn":[0.3892420365],"iteration":570,"passed_time":14.54097304,"remaining_time":10.92482913},
{"learn":[0.3892416481],"iteration":571,"passed_time":14.55742909,"remaining_time":10.89262177},
{"learn":[0.3892347143],"iteration":572,"passed_time":14.58570177,"remaining_time":10.86927514},
{"learn":[0.3892293594],"iteration":573,"passed_time":14.61228098,"remaining_time":10.84465453},
{"learn":[0.3892255376],"iteration":574,"passed_time":14.6360075,"remaining_time":10.81791859},
{"learn":[0.3892187553],"iteration":575,"passed_time":14.66757248,"remaining_time":10.79696308},
{"learn":[0.3892149939],"iteration":576,"passed_time":14.68838033,"remaining_time":10.76808471},
{"learn":[0.3889453156],"iteration":577,"passed_time":14.71555075,"remaining_time":10.74387961},
{"learn":[0.3889387722],"iteration":578,"passed_time":14.73931662,"remaining_time":10.71718877},
{"learn":[0.388934272],"iteration":579,"passed_time":14.75893542,"remaining_time":10.68750496},
{"learn":[0.3889339272],"iteration":580,"passed_time":14.78038823,"remaining_time":10.65917843},
{"learn":[0.3889269252],"iteration":581,"passed_time":14.80546199,"remaining_time":10.63347614},
{"learn":[0.3889256575],"iteration":582,"passed_time":14.82750601,"remaining_time":10.60560893},
{"learn":[0.3889116438],"iteration":583,"passed_time":14.86147743,"remaining_time":10.58625789},
{"learn":[0.3888429245],"iteration":584,"passed_time":14.89046455,"remaining_time":10.56332101},
{"learn":[0.3888426257],"iteration":585,"passed_time":14.91244748,"remaining_time":10.53541512},
{"learn":[0.3888422742],"iteration":586,"passed_time":14.93421588,"remaining_time":10.50737846},
{"learn":[0.3888018261],"iteration":587,"passed_time":14.95944564,"remaining_time":10.48178844},
{"learn":[0.3888018261],"iteration":588,"passed_time":14.97444932,"remaining_time":10.44906396},
{"learn":[0.3887997385],"iteration":589,"passed_time":14.99965658,"remaining_time":10.42349017},
{"learn":[0.3887968397],"iteration":590,"passed_time":15.02649716,"remaining_time":10.39904795},
{"learn":[0.3887947868],"iteration":591,"passed_time":15.05163065,"remaining_time":10.37342112},
{"learn":[0.388793256],"iteration":592,"passed_time":15.07677869,"remaining_time":10.34780595},
{"learn":[0.3887932508],"iteration":593,"passed_time":15.08896455,"remaining_time":10.31333267},
{"learn":[0.3887897474],"iteration":594,"passed_time":15.10915286,"remaining_time":10.28438136},
{"learn":[0.3887779916],"iteration":595,"passed_time":15.13333242,"remaining_time":10.25816493},
{"learn":[0.3887752259],"iteration":596,"passed_time":15.16097467,"remaining_time":10.23429278},
{"learn":[0.3887652913],"iteration":597,"passed_time":15.18438021,"remaining_time":10.20755994},
{"learn":[0.3887643667],"iteration":598,"passed_time":15.20714602,"remaining_time":10.18040994},
{"learn":[0.3887643641],"iteration":599,"passed_time":15.22403921,"remaining_time":10.14935948},
{"learn":[0.3887623165],"iteration":600,"passed_time":15.24218757,"remaining_time":10.11918942},
{"learn":[0.3887558088],"iteration":601,"passed_time":15.26294387,"remaining_time":10.09078349},
{"learn":[0.3887546677],"iteration":602,"passed_time":15.28002224,"remaining_time":10.05998147},
{"learn":[0.3887528796],"iteration":603,"passed_time":15.30975688,"remaining_time":10.03752272},
{"learn":[0.3887509428],"iteration":604,"passed_time":15.33304146,"remaining_time":10.01082872},
{"learn":[0.3887477418],"iteration":605,"passed_time":15.35297061,"remaining_time":9.981964392},
{"learn":[0.3887432414],"iteration":606,"passed_time":15.38164239,"remaining_time":9.958789885},
{"learn":[0.3887298164],"iteration":607,"passed_time":15.40705875,"remaining_time":9.933498403},
{"learn":[0.3887258031],"iteration":608,"passed_time":15.42632428,"remaining_time":9.904257464},
{"learn":[0.3887088904],"iteration":609,"passed_time":15.44829501,"remaining_time":9.876778775},
{"learn":[0.3887088859],"iteration":610,"passed_time":15.46217969,"remaining_time":9.844170048},
{"learn":[0.3887087737],"iteration":611,"passed_time":15.48394476,"remaining_time":9.816618571},
{"learn":[0.3886991335],"iteration":612,"passed_time":15.51199512,"remaining_time":9.793054014},
{"learn":[0.3886935068],"iteration":613,"passed_time":15.54203429,"remaining_time":9.770725138},
{"learn":[0.3886935024],"iteration":614,"passed_time":15.56119364,"remaining_time":9.741560249},
{"learn":[0.3886935001],"iteration":615,"passed_time":15.57714581,"remaining_time":9.710428557},
{"learn":[0.3886901306],"iteration":616,"passed_time":15.60279126,"remaining_time":9.685363133},
{"learn":[0.3886864431],"iteration":617,"passed_time":15.62538409,"remaining_time":9.658408939},
{"learn":[0.3886861475],"iteration":618,"passed_time":15.64431406,"remaining_time":9.629214309},
{"learn":[0.3886843859],"iteration":619,"passed_time":15.67022394,"remaining_time":9.604330799},
{"learn":[0.3886840929],"iteration":620,"passed_time":15.6935367,"remaining_time":9.577858954},
{"learn":[0.3886838015],"iteration":621,"passed_time":15.71474261,"remaining_time":9.55011689},
{"learn":[0.3886812784],"iteration":622,"passed_time":15.74106717,"remaining_time":9.525493295},
{"learn":[0.3886802383],"iteration":623,"passed_time":15.76267232,"remaining_time":9.498020498},
{"learn":[0.3886799501],"iteration":624,"passed_time":15.78229421,"remaining_time":9.469376523},
{"learn":[0.3886796635],"iteration":625,"passed_time":15.80730275,"remaining_time":9.4439796},
{"learn":[0.3886767068],"iteration":626,"passed_time":15.83377192,"remaining_time":9.419452831},
{"learn":[0.3886767051],"iteration":627,"passed_time":15.85246884,"remaining_time":9.390315937},
{"learn":[0.3886749809],"iteration":628,"passed_time":15.87735312,"remaining_time":9.364861697},
{"learn":[0.3886734387],"iteration":629,"passed_time":15.90125027,"remaining_time":9.338829523},
{"learn":[0.3886733336],"iteration":630,"passed_time":15.91682564,"remaining_time":9.307937656},
{"learn":[0.388670885],"iteration":631,"passed_time":15.94413032,"remaining_time":9.283923983},
{"learn":[0.3886434185],"iteration":632,"passed_time":15.96673683,"remaining_time":9.257176011},
{"learn":[0.3886424034],"iteration":633,"passed_time":15.99124424,"remaining_time":9.231538476},
{"learn":[0.3886399684],"iteration":634,"passed_time":16.02284842,"remaining_time":9.209983735},
{"learn":[0.3886198602],"iteration":635,"passed_time":16.05315331,"remaining_time":9.187653779},
{"learn":[0.3886195711],"iteration":636,"passed_time":16.07201022,"remaining_time":9.158775057},
{"learn":[0.3885876198],"iteration":637,"passed_time":16.09621442,"remaining_time":9.132961789},
{"learn":[0.3885873512],"iteration":638,"passed_time":16.12177489,"remaining_time":9.107919771},
{"learn":[0.3885873482],"iteration":639,"passed_time":16.1367027,"remaining_time":9.076895267},
{"learn":[0.3885048341],"iteration":640,"passed_time":16.16759408,"remaining_time":9.054861585},
{"learn":[0.388504831],"iteration":641,"passed_time":16.18061828,"remaining_time":9.022836983},
{"learn":[0.3885010809],"iteration":642,"passed_time":16.20490754,"remaining_time":8.997125959},
{"learn":[0.3885010673],"iteration":643,"passed_time":16.22514834,"remaining_time":8.969181381},
{"learn":[0.3885008052],"iteration":644,"passed_time":16.24366144,"remaining_time":8.940309785},
{"learn":[0.3884208689],"iteration":645,"passed_time":16.2784879,"remaining_time":8.92040978},
{"learn":[0.3884201073],"iteration":646,"passed_time":16.30652568,"remaining_time":8.896759761},
{"learn":[0.3884201042],"iteration":647,"passed_time":16.32195415,"remaining_time":8.8662467},
{"learn":[0.3884191366],"iteration":648,"passed_time":16.34019168,"remaining_time":8.837299353},
{"learn":[0.3884103483],"iteration":649,"passed_time":16.365214,"remaining_time":8.812038309},
{"learn":[0.388409598],"iteration":650,"passed_time":16.38353062,"remaining_time":8.783183081},
{"learn":[0.3884047075],"iteration":651,"passed_time":16.40942202,"remaining_time":8.758403164},
{"learn":[0.3883999371],"iteration":652,"passed_time":16.44390348,"remaining_time":8.738184546},
{"learn":[0.3883898785],"iteration":653,"passed_time":16.47012335,"remaining_time":8.713551499},
{"learn":[0.3883806856],"iteration":654,"passed_time":16.5024461,"remaining_time":8.692128097},
{"learn":[0.3883799717],"iteration":655,"passed_time":16.52603028,"remaining_time":8.666089048},
{"learn":[0.3883754881],"iteration":656,"passed_time":16.55409433,"remaining_time":8.642396278},
{"learn":[0.3883419334],"iteration":657,"passed_time":16.57734811,"remaining_time":8.616190053},
{"learn":[0.38825215],"iteration":658,"passed_time":16.59911941,"remaining_time":8.589225672},
{"learn":[0.3882521496],"iteration":659,"passed_time":16.61646535,"remaining_time":8.559997302},
{"learn":[0.388247701],"iteration":660,"passed_time":16.6459966,"remaining_time":8.537054232},
{"learn":[0.3882459832],"iteration":661,"passed_time":16.66821982,"remaining_time":8.510359968},
{"learn":[0.3882452955],"iteration":662,"passed_time":16.69358896,"remaining_time":8.485278249},
{"learn":[0.3882452912],"iteration":663,"passed_time":16.71184847,"remaining_time":8.456598022},
{"learn":[0.3882452909],"iteration":664,"passed_time":16.72636214,"remaining_time":8.426062131},
{"learn":[0.3882452898],"iteration":665,"passed_time":16.74066595,"remaining_time":8.395469111},
{"learn":[0.3882328511],"iteration":666,"passed_time":16.76992567,"remaining_time":8.372391676},
{"learn":[0.3882326177],"iteration":667,"passed_time":16.79151983,"remaining_time":8.345485905},
{"learn":[0.3882326137],"iteration":668,"passed_time":16.80650441,"remaining_time":8.315325798},
{"learn":[0.3882317189],"iteration":669,"passed_time":16.83061368,"remaining_time":8.289705247},
{"learn":[0.3882275237],"iteration":670,"passed_time":16.85827771,"remaining_time":8.265832143},
{"learn":[0.3882266421],"iteration":671,"passed_time":16.8808912,"remaining_time":8.239482608},
{"learn":[0.3882265559],"iteration":672,"passed_time":16.89845224,"remaining_time":8.210689273},
{"learn":[0.3882231026],"iteration":673,"passed_time":16.92028426,"remaining_time":8.183995056},
{"learn":[0.388217591],"iteration":674,"passed_time":16.94548662,"remaining_time":8.158938001},
{"learn":[0.3882076117],"iteration":675,"passed_time":16.97712557,"remaining_time":8.136965508},
{"learn":[0.3882073877],"iteration":676,"passed_time":16.99690334,"remaining_time":8.109305432},
{"learn":[0.3882073844],"iteration":677,"passed_time":17.01417121,"remaining_time":8.08047659},
{"learn":[0.3882071616],"iteration":678,"passed_time":17.03390822,"remaining_time":8.052849098},
{"learn":[0.3882065135],"iteration":679,"passed_time":17.06875331,"remaining_time":8.032354498},
{"learn":[0.3882046536],"iteration":680,"passed_time":17.09795326,"remaining_time":8.009173409},
{"learn":[0.3882046502],"iteration":681,"passed_time":17.11321739,"remaining_time":7.979476732},
{"learn":[0.388204647],"iteration":682,"passed_time":17.13368494,"remaining_time":7.952237375},
{"learn":[0.3882007788],"iteration":683,"passed_time":17.16299581,"remaining_time":7.929103325},
{"learn":[0.38820056],"iteration":684,"passed_time":17.18340009,"remaining_time":7.901855514},
{"learn":[0.3882005598],"iteration":685,"passed_time":17.20489247,"remaining_time":7.875125709},
{"learn":[0.3881953861],"iteration":686,"passed_time":17.23137907,"remaining_time":7.850686534},
{"learn":[0.3881953835],"iteration":687,"passed_time":17.24396788,"remaining_time":7.819938922},
{"learn":[0.3881937731],"iteration":688,"passed_time":17.2630532,"remaining_time":7.79217641},
{"learn":[0.3881935587],"iteration":689,"passed_time":17.2851002,"remaining_time":7.765769656},
{"learn":[0.3881929348],"iteration":690,"passed_time":17.3062884,"remaining_time":7.738991485},
{"learn":[0.3881697366],"iteration":691,"passed_time":17.32850303,"remaining_time":7.712686318},
{"learn":[0.3881648447],"iteration":692,"passed_time":17.3491097,"remaining_time":7.68568063},
{"learn":[0.3881648415],"iteration":693,"passed_time":17.37179113,"remaining_time":7.659608191},
{"learn":[0.388160329],"iteration":694,"passed_time":17.3945812,"remaining_time":7.633593189},
{"learn":[0.3881579292],"iteration":695,"passed_time":17.41557987,"remaining_time":7.606804999},
{"learn":[0.3881542758],"iteration":696,"passed_time":17.44421354,"remaining_time":7.583352514},
{"learn":[0.3881507127],"iteration":697,"passed_time":17.4761223,"remaining_time":7.561302197},
{"learn":[0.3881507094],"iteration":698,"passed_time":17.48945763,"remaining_time":7.531225676},
{"learn":[0.3881507061],"iteration":699,"passed_time":17.50291014,"remaining_time":7.501247201},
{"learn":[0.3881463569],"iteration":700,"passed_time":17.52759272,"remaining_time":7.476105881},
{"learn":[0.3881463569],"iteration":701,"passed_time":17.54631355,"remaining_time":7.448435097},
{"learn":[0.3881463569],"iteration":702,"passed_time":17.56577327,"remaining_time":7.421101938},
{"learn":[0.3881447133],"iteration":703,"passed_time":17.59636556,"remaining_time":7.398471883},
{"learn":[0.3881447101],"iteration":704,"passed_time":17.61221307,"remaining_time":7.369649439},
{"learn":[0.3881445107],"iteration":705,"passed_time":17.63455284,"remaining_time":7.343567328},
{"learn":[0.3881445077],"iteration":706,"passed_time":17.65409816,"remaining_time":7.316337711},
{"learn":[0.3881428842],"iteration":707,"passed_time":17.67823777,"remaining_time":7.291024618},
{"learn":[0.3881412904],"iteration":708,"passed_time":17.70286411,"remaining_time":7.265914607},
{"learn":[0.3881412874],"iteration":709,"passed_time":17.72024746,"remaining_time":7.237847553},
{"learn":[0.3881401883],"iteration":710,"passed_time":17.73932581,"remaining_time":7.210499521},
{"learn":[0.3881401857],"iteration":711,"passed_time":17.75933201,"remaining_time":7.183550025},
{"learn":[0.3881393932],"iteration":712,"passed_time":17.78000014,"remaining_time":7.156886451},
{"learn":[0.3880653383],"iteration":713,"passed_time":17.81235653,"remaining_time":7.134921525},
{"learn":[0.3880652377],"iteration":714,"passed_time":17.82787896,"remaining_time":7.106217487},
{"learn":[0.3880643864],"iteration":715,"passed_time":17.84754128,"remaining_time":7.079192353},
{"learn":[0.3880607523],"iteration":716,"passed_time":17.87608227,"remaining_time":7.055692163},
{"learn":[0.3880607508],"iteration":717,"passed_time":17.88959675,"remaining_time":7.026276163},
{"learn":[0.3880585395],"iteration":718,"passed_time":17.91362099,"remaining_time":7.001011819},
{"learn":[0.3880579854],"iteration":719,"passed_time":17.9393696,"remaining_time":6.976421512},
{"learn":[0.3880578946],"iteration":720,"passed_time":17.95581088,"remaining_time":6.948226403},
{"learn":[0.3880578931],"iteration":721,"passed_time":17.97335653,"remaining_time":6.92048908},
{"learn":[0.3880545656],"iteration":722,"passed_time":18.00081104,"remaining_time":6.896576291},
{"learn":[0.3880531318],"iteration":723,"passed_time":18.0210689,"remaining_time":6.869910245},
{"learn":[0.3880530211],"iteration":724,"passed_time":18.03800082,"remaining_time":6.84200031},
{"learn":[0.3880524744],"iteration":725,"passed_time":18.06294769,"remaining_time":6.817145549},
{"learn":[0.3880509013],"iteration":726,"passed_time":18.08772788,"remaining_time":6.792227939},
{"learn":[0.3880508998],"iteration":727,"passed_time":18.10067246,"remaining_time":6.76288861},
{"learn":[0.388019475],"iteration":728,"passed_time":18.12145233,"remaining_time":6.736506971},
{"learn":[0.3880192886],"iteration":729,"passed_time":18.14097047,"remaining_time":6.70967401},
{"learn":[0.388019103],"iteration":730,"passed_time":18.16042815,"remaining_time":6.682838813},
{"learn":[0.3880190851],"iteration":731,"passed_time":18.18040972,"remaining_time":6.65621558},
{"learn":[0.3880189004],"iteration":732,"passed_time":18.19856884,"remaining_time":6.62894663},
{"learn":[0.388012411],"iteration":733,"passed_time":18.23166544,"remaining_time":6.607115814},
{"learn":[0.3880111538],"iteration":734,"passed_time":18.26184047,"remaining_time":6.584200985},
{"learn":[0.3880104089],"iteration":735,"passed_time":18.28047418,"remaining_time":6.55712661},
{"learn":[0.388009022],"iteration":736,"passed_time":18.3026203,"remaining_time":6.531328548},
{"learn":[0.3880069227],"iteration":737,"passed_time":18.32780215,"remaining_time":6.506618108},
{"learn":[0.3880067434],"iteration":738,"passed_time":18.35001311,"remaining_time":6.480857133},
{"learn":[0.3880052185],"iteration":739,"passed_time":18.3742017,"remaining_time":6.455800598},
{"learn":[0.3880015254],"iteration":740,"passed_time":18.39815451,"remaining_time":6.430663991},
{"learn":[0.3880001588],"iteration":741,"passed_time":18.41939635,"remaining_time":6.404587949},
{"learn":[0.3880001571],"iteration":742,"passed_time":18.43743893,"remaining_time":6.37741831},
{"learn":[0.3879970381],"iteration":743,"passed_time":18.460928,"remaining_time":6.352147268},
{"learn":[0.3879962112],"iteration":744,"passed_time":18.47921802,"remaining_time":6.325101471},
{"learn":[0.387994745],"iteration":745,"passed_time":18.50595961,"remaining_time":6.300956756},
{"learn":[0.3879945982],"iteration":746,"passed_time":18.53393724,"remaining_time":6.277223725},
{"learn":[0.387993861],"iteration":747,"passed_time":18.56010458,"remaining_time":6.252869457},
{"learn":[0.3879938594],"iteration":748,"passed_time":18.5768431,"remaining_time":6.225350625},
{"learn":[0.3879919645],"iteration":749,"passed_time":18.59752801,"remaining_time":6.199176005},
{"learn":[0.3879905134],"iteration":750,"passed_time":18.61998474,"remaining_time":6.173603463},
{"learn":[0.3879891937],"iteration":751,"passed_time":18.64015458,"remaining_time":6.147285022},
{"learn":[0.3879880414],"iteration":752,"passed_time":18.65992089,"remaining_time":6.120850545},
{"learn":[0.3879880401],"iteration":753,"passed_time":18.67806679,"remaining_time":6.09390508},
{"learn":[0.3879838904],"iteration":754,"passed_time":18.70251401,"remaining_time":6.069027725},
{"learn":[0.3879838888],"iteration":755,"passed_time":18.72090801,"remaining_time":6.042197823},
{"learn":[0.3879837724],"iteration":756,"passed_time":18.73758275,"remaining_time":6.01483832},
{"learn":[0.3879806922],"iteration":757,"passed_time":18.76256606,"remaining_time":5.990159613},
{"learn":[0.3879806907],"iteration":758,"passed_time":18.77868672,"remaining_time":5.962666006},
{"learn":[0.3879794049],"iteration":759,"passed_time":18.79705502,"remaining_time":5.935912112},
{"learn":[0.3879763816],"iteration":760,"passed_time":18.81923952,"remaining_time":5.910378771},
{"learn":[0.3879734328],"iteration":761,"passed_time":18.84140321,"remaining_time":5.884847722},
{"learn":[0.387973268],"iteration":762,"passed_time":18.86543775,"remaining_time":5.859906613},
{"learn":[0.3879732663],"iteration":763,"passed_time":18.88149285,"remaining_time":5.832503025},
{"learn":[0.3879731273],"iteration":764,"passed_time":18.90679652,"remaining_time":5.807970174},
{"learn":[0.3879731258],"iteration":765,"passed_time":18.92159056,"remaining_time":5.780224791},
{"learn":[0.387969516],"iteration":766,"passed_time":18.9490857,"remaining_time":5.756371536},
{"learn":[0.3879695145],"iteration":767,"passed_time":18.96371683,"remaining_time":5.728622793},
{"learn":[0.3879687926],"iteration":768,"passed_time":18.98838191,"remaining_time":5.703922263},
{"learn":[0.3879687911],"iteration":769,"passed_time":19.00134332,"remaining_time":5.675725927},
{"learn":[0.3879674497],"iteration":770,"passed_time":19.02381969,"remaining_time":5.650395213},
{"learn":[0.3879656567],"iteration":771,"passed_time":19.04282218,"remaining_time":5.624045929},
{"learn":[0.3879625311],"iteration":772,"passed_time":19.0704104,"remaining_time":5.600236947},
{"learn":[0.3879625308],"iteration":773,"passed_time":19.0864759,"remaining_time":5.573053686},
{"learn":[0.3879612124],"iteration":774,"passed_time":19.1191997,"remaining_time":5.550735396},
{"learn":[0.3879599812],"iteration":775,"passed_time":19.14485954,"remaining_time":5.526351207},
{"learn":[0.3879599808],"iteration":776,"passed_time":19.15915852,"remaining_time":5.498703152},
{"learn":[0.3879284815],"iteration":777,"passed_time":19.18031628,"remaining_time":5.473046548},
{"learn":[0.3879284545],"iteration":778,"passed_time":19.20433341,"remaining_time":5.448212687},
{"learn":[0.3879258124],"iteration":779,"passed_time":19.22573151,"remaining_time":5.42264222},
{"learn":[0.3879230113],"iteration":780,"passed_time":19.25913595,"remaining_time":5.400449133},
{"learn":[0.3879221466],"iteration":781,"passed_time":19.27570338,"remaining_time":5.37353368},
{"learn":[0.3879214875],"iteration":782,"passed_time":19.29679311,"remaining_time":5.347897962},
{"learn":[0.3879210794],"iteration":783,"passed_time":19.32043019,"remaining_time":5.322975665},
{"learn":[0.387921078],"iteration":784,"passed_time":19.33535949,"remaining_time":5.295671707},
{"learn":[0.387921078],"iteration":785,"passed_time":19.35913068,"remaining_time":5.270806572},
{"learn":[0.387918325],"iteration":786,"passed_time":19.38968237,"remaining_time":5.247779345},
{"learn":[0.3879170672],"iteration":787,"passed_time":19.41432799,"remaining_time":5.223144078}
]}